Metadata-Version: 1.0
Name: binomial-gaussian-distributions-ldz
Version: 1.0
Summary: Gaussian and Binomial distributions
Home-page: UNKNOWN
Author: UNKNOWN
Author-email: ldzarzec@syr.edu
License: UNKNOWN
Platform: UNKNOWN
